{
  "department": "dining",
  "process_name": "تمیزکردن بهداشتی سینی‌ها و تحویل به آشپزخانه",
  "summary": "پس از پایان غذای مشتری و جمع‌آوری میز، جونیور سینی‌ها را در باکس مخصوص هر بخش قرار می‌دهد و پس از انباشته‌شدن چند سینی (پنج تا شش سینی)، آن‌ها را با هم به قسمت پایین/کانتر می‌برد. در آنجا ابتدا زباله‌های روی سینی تفکیک می‌شود (قوطی و بطری قابل بازیافت از سایر زباله‌ها جدا می‌شود)، سپس سینی‌ها به صورت کاملاً بهداشتی با الکل یا شیشه‌شوی با درصد الکل بالا و با دستمال و اسپری مخصوص تمیز می‌شوند. پس از تمیزکاری، جونیور گوشه‌ها و لبه‌های سینی را چک می‌کند و در نهایت سینی تمیز به آشپزخانه (کانترکار آشپزخانه) تحویل داده می‌شود تا دوباره برای سرو غذا استفاده شود.",
  "idef0": {
    "inputs": ["سینی‌های استفاده‌شده", "زباله‌های روی سینی"],
    "controls": ["استاندارد بهداشتی تمیزی سینی", "اصل وحدت فرماندهی در ارتباط با آشپزخانه", "قانون بهداشت تفکیک زباله"],
    "outputs": ["سینی تمیزِ بهداشتی تحویل‌شده به آشپزخانه", "زباله تفکیک‌شده"],
    "mechanisms": ["جونیور", "کانترکار آشپزخانه", "دستمال مخصوص", "اسپری مخصوص", "الکل یا شیشه‌شوی با درصد الکل بالا"]
  },
  "kpis": [],
  "nodes": [
    {
      "key": "n1",
      "type": "activity",
      "label": "قرار دادن سینی‌های استفاده‌شده در باکس مخصوص هر بخش",
      "description": "پس از جمع‌آوری میز، جونیور سینی را با خود می‌برد و در باکس جداگانه‌ای که در هر بخش (تراس، داخل سالن، طبقه بالا) قرار دارد می‌گذارد.",
      "actor": "جونیور",
      "icom": {
        "inputs": ["سینی‌های استفاده‌شده"],
        "controls": [],
        "outputs": ["سینی‌های انباشته‌شده در باکس"],
        "mechanisms": ["جونیور", "باکس مخصوص هر بخش"]
      },
      "subprocess": null
    },
    {
      "key": "n2",
      "type": "activity",
      "label": "بردن چند سینی انباشته‌شده به قسمت پایین برای تمیز کردن",
      "description": "پس از اینکه سینی‌ها جمع شد، مثلاً پنج تا شش سینی را با هم برمی‌دارند و به قسمت پایین/کانتر می‌برند. در شعبه ناهارخوران که کانتر و محل نگهداری طولانی‌مدت سینی وجود ندارد، بچه‌ها باید سریع‌تر سینی را تحویل دهند.",
      "actor": "جونیور",
      "icom": {
        "inputs": ["سینی‌های انباشته‌شده در باکس"],
        "controls": [],
        "outputs": [],
        "mechanisms": ["جونیور"]
      },
      "subprocess": null
    },
    {
      "key": "n3",
      "type": "activity",
      "label": "تفکیک زباله‌های روی سینی",
      "description": "زباله‌های قوطی یا بطری که قابل بازیافت هستند از زباله‌های دیگر تفکیک می‌شوند و در سطل زباله جداگانه ریخته می‌شوند.",
      "actor": "جونیور",
      "icom": {
        "inputs": ["زباله‌های روی سینی"],
        "controls": ["قانون بهداشت تفکیک زباله"],
        "outputs": ["زباله تفکیک‌شده"],
        "mechanisms": ["جونیور"]
      },
      "subprocess": null
    },
    {
      "key": "n4",
      "type": "activity",
      "label": "تمیزکردن بهداشتی سینی با الکل یا شیشه‌شوی با درصد الکل بالا",
      "description": "سینی‌ها حتماً به صورت کاملاً بهداشتی تمیز می‌شوند؛ با الکل یا شیشه‌شوی با درصد الکل بالا و با دستمال و اسپری مخصوص که برای تمیز کردن سینی‌ها در نظر گرفته شده است.",
      "actor": "جونیور",
      "icom": {
        "inputs": ["سینی استفاده‌شده"],
        "controls": ["استاندارد بهداشتی تمیزی سینی"],
        "outputs": ["سینی تمیزِ بهداشتی"],
        "mechanisms": ["جونیور", "دستمال مخصوص", "اسپری مخصوص", "الکل یا شیشه‌شوی با درصد الکل بالا"]
      },
      "subprocess": null
    },
    {
      "key": "n5",
      "type": "activity",
      "label": "چک کردن گوشه‌ها و لبه‌های سینی پس از تمیزکاری",
      "description": "پس از تمیزشدن سینی، یک بار توسط همان جونیورِ تفکیک، گوشه‌ها و لبه‌های سینی چک می‌شود تا از تمیزی کامل آن اطمینان حاصل شود.",
      "actor": "جونیور",
      "icom": {
        "inputs": ["سینی تمیزِ بهداشتی"],
        "controls": ["استاندارد بهداشتی تمیزی سینی"],
        "outputs": [],
        "mechanisms": ["جونیور"]
      },
      "subprocess": null
    },
    {
      "key": "n6",
      "type": "activity",
      "label": "تحویل سینی تمیز به کانترکار آشپزخانه",
      "description": "سینی تمیز به آشپزخانه (کانترکار آشپزخانه) تحویل داده می‌شود؛ آشپزخانه دوباره همان سینی‌ها را استفاده می‌کند و روی آن غذا می‌گذارد و به سالن تحویل می‌دهد. طبق اصل وحدت فرماندهی، سالن در آشپزخانه فقط با کانترکار (و در نبود او سرپرست آشپزخانه) در ارتباط است.",
      "actor": "جونیور",
      "icom": {
        "inputs": ["سینی تمیزِ بهداشتی"],
        "controls": ["اصل وحدت فرماندهی در ارتباط با آشپزخانه"],
        "outputs": ["سینی تمیز تحویل‌شده به آشپزخانه"],
        "mechanisms": ["جونیور", "کانترکار آشپزخانه"]
      },
      "subprocess": null
    }
  ],
  "edges": [
    { "from": "n1", "to": "n2", "label": "پس از انباشته‌شدن پنج تا شش سینی" },
    { "from": "n2", "to": "n3" },
    { "from": "n3", "to": "n4" },
    { "from": "n4", "to": "n5" },
    { "from": "n5", "to": "n6" }
  ]
}
